odoo/addons/portal_eater/README.rst
odoo/addons/portal_eater/__init__.py
odoo/addons/portal_eater/__manifest__.py
odoo/addons/portal_eater/controllers/__init__.py
odoo/addons/portal_eater/controllers/portal.py
odoo/addons/portal_eater/i18n/portal_eater.pot
odoo/addons/portal_eater/readme/CONTRIBUTORS.rst
odoo/addons/portal_eater/readme/DESCRIPTION.rst
odoo/addons/portal_eater/static/description/index.html
odoo/addons/portal_eater/views/portal_eater_templates.xml
odoo_addon_portal_eater-16.0.1.0.0.3.dist-info/METADATA
odoo_addon_portal_eater-16.0.1.0.0.3.dist-info/WHEEL
odoo_addon_portal_eater-16.0.1.0.0.3.dist-info/top_level.txt
odoo_addon_portal_eater-16.0.1.0.0.3.dist-info/RECORD
