Metadata-Version: 2.1
Name: odoo-addon-portal_eater
Version: 16.0.1.0.0.3
Requires-Python: >=3.10
Requires-Dist: odoo-addon-eater>=16.0dev,<16.1dev
Requires-Dist: odoo>=16.0a,<16.1dev
Summary: Show the eaters of a cooperator in the website portal.
Home-page: https://github.com/beescoop/Obeesdoo
License: AGPL-3
Author: =?utf-8?q?R=C3=A9my_Taymans=2C_Coop_IT_Easy_SC?=
Classifier: Programming Language :: Python
Classifier: Framework :: Odoo
Classifier: Framework :: Odoo :: 16.0
Classifier: License :: OSI Approved :: GNU Affero General Public License v3
